{
  "OFFICIAL_PAGE_KEYWORDS": [
    "about",
    "our-story",
    "who-we-are",
    "values",
    "mission",
    "sustainability",
    "responsibility",
    "impact",
    "esg",
    "environment",
    "climate",
    "carbon",
    "emissions",
    "net-zero",
    "netzero",
    "decarbonisation",
    "decarbonization",
    "materials",
    "material",
    "fibres",
    "fibers",
    "cotton",
    "polyester",
    "recycled",
    "organic",
    "regenerative",
    "viscose",
    "supply-chain",
    "supplychain",
    "suppliers",
    "supplier-list",
    "factory",
    "factories",
    "traceability",
    "transparency",
    "human-rights",
    "labour",
    "labor",
    "workers",
    "wages",
    "modern-slavery",
    "forced-labour",
    "forced-labor",
    "circular",
    "circularity",
    "repair",
    "resale",
    "reuse",
    "recycling",
    "take-back",
    "takeback",
    "garment-collection",
    "annual-report",
    "sustainability-report",
    "impact-report",
    "esg-report",
    "modern-slavery-statement",
    "certifications",
    "certified",
    "gots",
    "fairtrade",
    "oeko-tex",
    "oekotex",
    "bluesign",
    "b-corp",
    "fair-wear"
  ],
  "TOPICS": {
    "carbon_emissions": [
      "carbon emissions",
      "greenhouse gas",
      "ghg",
      "scope 1",
      "scope 2",
      "scope 3",
      "net zero",
      "climate target",
      "carbon footprint",
      "decarbonisation",
      "decarbonization",
      "renewable energy",
      "science based targets",
      "sbt",
      "emissions reduction"
    ],
    "labour_practices": [
      "worker rights",
      "fair wages",
      "living wage",
      "factory conditions",
      "labour standards",
      "labor standards",
      "forced labour",
      "forced labor",
      "child labour",
      "child labor",
      "human rights",
      "modern slavery",
      "collective bargaining",
      "working hours",
      "health and safety"
    ],
    "material_sourcing": [
      "organic cotton",
      "recycled cotton",
      "recycled polyester",
      "responsible wool",
      "responsible viscose",
      "tencel",
      "lyocell",
      "linen",
      "hemp",
      "regenerative cotton",
      "preferred materials",
      "certified materials",
      "material composition",
      "fiber sourcing",
      "fibre sourcing"
    ],
    "supply_chain_transparency": [
      "supplier list",
      "factory list",
      "factory disclosure",
      "tier 1",
      "tier 2",
      "tier 3",
      "traceability",
      "supply chain",
      "audit",
      "supplier code of conduct",
      "manufacturing partners",
      "production country",
      "factory locations"
    ],
    "circular_fashion": [
      "circular fashion",
      "circularity",
      "repair",
      "resale",
      "reuse",
      "rental",
      "take back",
      "take-back",
      "garment collection",
      "closed loop",
      "product lifecycle",
      "durability",
      "repair service"
    ],
    "greenwashing_allegations": [
      "greenwashing",
      "misleading claims",
      "false sustainability claims",
      "unsubstantiated claims",
      "vague claims",
      "lawsuit",
      "investigation",
      "accused",
      "consumer deception",
      "misleading marketing"
    ],
    "recycling_initiatives": [
      "recycling",
      "recycled materials",
      "textile waste",
      "post-consumer waste",
      "pre-consumer waste",
      "closed loop recycling",
      "garment recycling",
      "waste reduction",
      "recycled fibers",
      "recycled fibres"
    ],
    "water_management": [
      "water use",
      "water consumption",
      "water footprint",
      "wastewater",
      "water pollution",
      "dyeing",
      "chemical discharge",
      "water stewardship",
      "wet processing"
    ],
    "chemical_management": [
      "chemical management",
      "restricted substances",
      "hazardous chemicals",
      "zdhc",
      "detox",
      "dyes",
      "finishing chemicals",
      "chemical safety",
      "oeko-tex",
      "bluesign"
    ],
    "animal_welfare": [
      "animal welfare",
      "wool",
      "leather",
      "down",
      "mulesing",
      "responsible wool standard",
      "responsible down standard",
      "cruelty-free",
      "fur-free",
      "vegan leather"
    ],
    "certifications": [
      "gots",
      "fairtrade",
      "oeko-tex",
      "bluesign",
      "fair wear foundation",
      "b corp",
      "global recycled standard",
      "grs",
      "responsible wool standard",
      "rws",
      "fsc",
      "rainforest alliance"
    ],
    "reporting_and_governance": [
      "sustainability report",
      "annual report",
      "impact report",
      "esg report",
      "third-party assurance",
      "independent verification",
      "kpi",
      "progress update",
      "governance",
      "board oversight"
    ]
  },
  "VAGUE_GREENWASHING_WORDS": [
    "eco-friendly",
    "green",
    "conscious",
    "planet-friendly",
    "better for the planet",
    "responsible",
    "sustainable choice",
    "kind to the planet",
    "earth friendly",
    "good for the planet",
    "low impact",
    "natural",
    "clean",
    "ethical collection",
    "conscious collection"
  ],
  "CERTIFICATION_NAMES": [
    "GOTS",
    "Fairtrade",
    "OEKO-TEX",
    "Bluesign",
    "Fair Wear Foundation",
    "GRS",
    "B Corp",
    "Responsible Wool Standard",
    "RWS",
    "FSC",
    "ZDHC",
    "Cradle to Cradle"
  ],
  "MATERIAL_TERMS": [
    "organic cotton",
    "recycled cotton",
    "recycled polyester",
    "cotton",
    "polyester",
    "linen",
    "wool",
    "responsible wool",
    "viscose",
    "responsible viscose",
    "tencel",
    "lyocell",
    "recycled nylon",
    "nylon",
    "hemp",
    "leather",
    "vegan leather",
    "elastane",
    "polyamide",
    "acrylic",
    "modal",
    "cashmere",
    "silk",
    "down",
    "recycled wool"
  ],
  "SUSTAINABLE_MATERIAL_TERMS": [
    "organic cotton",
    "recycled cotton",
    "recycled polyester",
    "recycled nylon",
    "recycled wool",
    "linen",
    "hemp",
    "tencel",
    "lyocell",
    "responsible wool",
    "responsible viscose",
    "regenerative cotton"
  ],
  "PRODUCT_CATEGORIES": {
    "t-shirt": [
      "t-shirt",
      "tee",
      "shirt"
    ],
    "jeans": [
      "jeans",
      "denim"
    ],
    "dress": [
      "dress"
    ],
    "jacket": [
      "jacket",
      "coat",
      "blazer"
    ],
    "shoes": [
      "shoes",
      "sneakers",
      "boots"
    ],
    "bag": [
      "bag",
      "tote",
      "handbag"
    ],
    "sweater": [
      "sweater",
      "jumper",
      "knitwear"
    ],
    "skirt": [
      "skirt"
    ],
    "trousers": [
      "trousers",
      "pants"
    ]
  },
  "NEWS_RSS_FEEDS": [
    "https://www.theguardian.com/fashion/rss",
    "https://www.theguardian.com/business/rss",
    "https://feeds.bbci.co.uk/news/business/rss.xml",
    "https://feeds.bbci.co.uk/news/rss.xml"
  ],
  "CERTIFICATION_HOMEPAGES": [
    "https://global-standard.org",
    "https://www.fairtrade.net",
    "https://www.oeko-tex.com",
    "https://www.bluesign.com",
    "https://www.fairwear.org",
    "https://textileexchange.org",
    "https://www.bcorporation.net"
  ]
}